MrDatabase-0.9.8.dist-info/METADATA
MrDatabase-0.9.8.dist-info/RECORD
MrDatabase-0.9.8.dist-info/WHEEL
MrDatabase-0.9.8.dist-info/top_level.txt
database/__init__.py
database/column.py
database/data_formatting.py
database/databaseconnection.py
database/mrdatabase.py
database/records.py
database/table.py
mr_database/__init__.py
mr_database/column.py
mr_database/data_formatting.py
mr_database/databaseconnection.py
mr_database/mrdatabase.py
mr_database/records.py
mr_database/table.py
pyside2_models/__init__.py
pyside2_models/local_table_model.py
samples/__init__.py
samples/demo.py
samples/demo_blob.py
samples/pyside2_table_model.py
samples/table_schema_examples.py
tests/__init__.py
tests/database_tests.py
