Metadata-Version: 2.1
Name: MrDatabase
Version: 0.9.8
Summary: Databasing as easy as it gets!
Home-page: https://github.com/SorenSeeberg/MrDatabase
Author: Seeberg
Author-email: soren.seeberg@gmail.com
License: UNKNOWN
Platform: UNKNOWN
Classifier: Programming Language :: Python :: 3.6
Classifier: License :: OSI Approved :: MIT License
Classifier: Operating System :: OS Independent
